sb_picsou/__init__.py
sb_picsou/picsou.py
sb_picsou-0.1.0.dist-info/METADATA
sb_picsou-0.1.0.dist-info/WHEEL
sb_picsou-0.1.0.dist-info/RECORD
