Metadata-Version: 2.1
Name: sb-picsou
Version: 0.1.0
Summary: 
Author: saadbouhya
Author-email: bouhyasaad@gmail.com
Requires-Python: ==3.10.11
Classifier: Programming Language :: Python :: 3
Requires-Dist: coverage (==7.4.1)
Requires-Dist: pillow (==10.2.0)
